spec_pilot/__init__.py
spec_pilot/generator.py
spec_pilot/language_processor.py
spec_pilot/main.py
spec_pilot/prompt_builder.py
spec_pilot/validator.py
spec_pilot-0.3.4.dist-info/LICENSE
spec_pilot-0.3.4.dist-info/METADATA
spec_pilot-0.3.4.dist-info/WHEEL
spec_pilot-0.3.4.dist-info/entry_points.txt
spec_pilot-0.3.4.dist-info/top_level.txt
spec_pilot-0.3.4.dist-info/RECORD
