Metadata-Version: 2.1
Name: spec-pilot
Version: 0.3.4
Summary: A command-line tool for generating and managing OpenAPI specifications
Home-page: https://github.com/jmfwolf/spec-pilot
Author: jmfwolf
Author-email: jmfwolf@hacksomniac.com
Classifier: Development Status :: 3 - Alpha
Classifier: Intended Audience :: Developers
Classifier: License :: OSI Approved :: GNU General Public License v3 (GPLv3)
Classifier: Operating System :: OS Independent
Classifier: Programming Language :: Python :: 3
Classifier: Programming Language :: Python :: 3.6
Classifier: Programming Language :: Python :: 3.7
Classifier: Programming Language :: Python :: 3.8
Classifier: Programming Language :: Python :: 3.9
Classifier: Programming Language :: Python :: 3.10
Requires-Python: >=3.6
License-File: LICENSE
Requires-Dist: blis (==0.7.9)
Requires-Dist: catalogue (==2.0.8)
Requires-Dist: certifi (==2023.5.7)
Requires-Dist: charset-normalizer (==3.1.0)
Requires-Dist: click (==8.1.3)
Requires-Dist: confection (==0.0.4)
Requires-Dist: cymem (==2.0.7)
Requires-Dist: idna (==3.4)
Requires-Dist: Jinja2 (==3.1.2)
Requires-Dist: langcodes (==3.3.0)
Requires-Dist: MarkupSafe (==2.1.2)
Requires-Dist: murmurhash (==1.0.9)
Requires-Dist: numpy (==1.24.3)
Requires-Dist: packaging (==23.1)
Requires-Dist: pathy (==0.10.1)
Requires-Dist: preshed (==3.0.8)
Requires-Dist: pydantic (==1.10.7)
Requires-Dist: pystache (==0.6.0)
Requires-Dist: PyYAML (==6.0)
Requires-Dist: requests (==2.30.0)
Requires-Dist: smart-open (==6.3.0)
Requires-Dist: spacy (==3.5.2)
Requires-Dist: spacy-legacy (==3.0.12)
Requires-Dist: spacy-loggers (==1.0.4)
Requires-Dist: srsly (==2.4.6)
Requires-Dist: thinc (==8.1.10)
Requires-Dist: tqdm (==4.65.0)
Requires-Dist: typer (==0.7.0)
Requires-Dist: typing-extensions (==4.5.0)
Requires-Dist: urllib3 (==2.0.2)
Requires-Dist: wasabi (==1.1.1)
